fsm.v
// Logical Module 
module fsm (
    input wire clk,      // Clock signal
    input wire reset,    // Reset signal to initialize the state
    input wire coin,     // Input signal - 1 bit to insert the coin 
    input wire push,     // Input signal - 1 bit to push 
    output reg state     // Output state: 0 = LOCKED, 1 = UNLOCKED
);

// Define states of FSM - 0 = LOCKED, 1 = UNLOCKED
parameter LOCKED = 1'b0, UNLOCKED = 1'b1;

// working_state signal to store the current state
reg working_state;

// Sequential logic to update the current state or reset
always @(posedge clk or posedge reset) begin
    if (reset) 
        working_state <= LOCKED; // set current state to LOCKED = 0 
    else begin
        case (working_state)
            LOCKED: begin  // Case Locked
                if (coin) 
                    working_state <= UNLOCKED; // Insert coin will unlock the turnstile
                else 
                    working_state <= LOCKED; // Stay in locked state
            end
            UNLOCKED: begin // Case Unlocked
                if (push) 
                    working_state <= LOCKED; // Push to lock the turnstile
                else 
                    working_state <= UNLOCKED; // Stay in unlocked state
            end
            default: // Default state of switch case statement is LOCKED
                working_state <= LOCKED; 
        endcase // end swith case 
    end
end

// Output logic to show the state of turnstile
always @(*) begin
    state = working_state; // Output current based on the working_state
end

endmodule

fsm_tb.v
`include "fsm.v" // Include logical module to test bench - for compiling we need to use iverilog -o xyz nameoftestbenchfile.v 

module fsm_tb();
// Testbench signals I/O 
reg clk;           // Clock signal
reg reset;         // Reset signal
reg COIN;          // Coin input
reg PUSH;          // Push input
wire fsm_state;        // State output from fsm logical module
reg[10*8:0] string_state; // Handle strings in Verilog - each character is 8 ASCII bits



// Instantiate the fsm logical module
fsm uut (
    .clk(clk),
    .reset(reset),
    .coin(COIN),
    .push(PUSH),
    .state(fsm_state)
);

// Static Task / Function to insert a coin 
task insert_coin;
    begin
        #10; //wait 10 time units 
        COIN = 1; 
        #10; //wait 10 time units 
        COIN = 0;
    end 
endtask

// Static Task / Function to push 
task push;
    begin 
        #10; //wait 10 time units 
        PUSH = 1;
        #10; //wait 10 time units 
        PUSH = 0;
    end
endtask

// Clock generation 
initial begin
    clk = 0;
    forever #10 clk = ~clk; // Toggle clock every 10 time period
end

// Test fsm logic
initial begin
    // generate dumpfile even if we don't have GTKwave
    $dumpfile("fsm.vcd"); 
    $dumpvars(0, fsm_tb);
    // Initial conditions
    $display("*** Starting Testbench for fsm *** \n");
    reset = 1; COIN = 0; PUSH = 0;   // Start with reset active, coin and push = 0 
    #20                             // Wait for two clock cycles, 20 time units 
    reset = 0;                     // Release reset and set to 0 

    // Test Case 1: Insert coin when turnstile locked
    $display("\nTest 1: Insert coin when the turnstile state is %s \n", string_state);
    insert_coin();

    // Test Case 2: Push when turnstile unlocked
    $display("\nTest 2: Push when the turnstile state is %s \n", string_state);
    push();

    // Test Case 3: Push when turnstile locked
    $display("\nTest 3: Push when the turnstile state is %s \n", string_state);
    push();

    // Test Case 4: Insert coin when turnstile unlocked
    $display("\nTest 4: Insert coin when the turnstile state is %s \n", string_state);
    insert_coin();

    // Finish simulation 
    #40;                          // wait 40 time unit
    $display("\nTurnstile Simulation Complete. \n");
    $finish;
end

// Handle string and assign value based on the fsm_state
always @(*) begin
    if (fsm_state)
        string_state = "UNLOCKED"; // if state is 1 --> string = UNLOCKED 
    else 
        string_state = "LOCKED";  // is state is 0 --> string = LOCKED 
end

// Monitor the result of the test, we don't have GTKwave available
initial begin
    $monitor("At time %t: reset = %b, COIN = %b, PUSH = %b, fsm_state = %s",
             $time, reset, COIN, PUSH, string_state);
end

endmodule

fsm.vcd
$date
	Mon Dec  9 21:26:25 2024
$end
$version
	Icarus Verilog
$end
$timescale
	1s
$end
$scope module fsm_tb $end
$var wire 1 ! fsm_state $end
$var reg 1 " COIN $end
$var reg 1 # PUSH $end
$var reg 1 $ clk $end
$var reg 1 % reset $end
$var reg 81 & string_state [80:0] $end
$scope module uut $end
$var wire 1 $ clk $end
$var wire 1 " coin $end
$var wire 1 # push $end
$var wire 1 % reset $end
$var parameter 1 ' LOCKED $end
$var parameter 1 ( UNLOCKED $end
$var reg 1 ! state $end
$var reg 1 ) working_state $end
$upscope $end
$scope task insert_coin $end
$upscope $end
$scope task push $end
$upscope $end
$upscope $end
$enddefinitions $end
$comment Show the parameter values. $end
$dumpall
1(
0'
$end
#0
$dumpvars
0)
b10011000100111101000011010010110100010101000100 &
1%
0$
0#
0"
0!
$end
#10
1$
#20
0$
0%
#30
b101010101001110010011000100111101000011010010110100010101000100 &
1!
1)
1$
1"
#40
0$
0"
#50
b10011000100111101000011010010110100010101000100 &
0!
0)
1$
1#
#60
0$
0#
#70
1$
1#
#80
0$
0#
#90
b101010101001110010011000100111101000011010010110100010101000100 &
1!
1)
1$
1"
#100
0$
0"
